pylint_blocking_calls/__init__.py
pylint_blocking_calls/blocking_calls.py
pylint_blocking_calls/helpers.py
pylint_blocking_calls-0.1.0.dist-info/LICENSE
pylint_blocking_calls-0.1.0.dist-info/WHEEL
pylint_blocking_calls-0.1.0.dist-info/METADATA
pylint_blocking_calls-0.1.0.dist-info/RECORD
