Metadata-Version: 2.1
Name: pylint-blocking-calls
Version: 0.1.0
Summary: Pylint plugin to detect blocking calls in async functions
Home-page: https://github.com/Edge-Center/pylint-blocking-calls
License: MIT
Author: Aleksei Marashov
Author-email: marashov-aleksey@yandex.ru
Requires-Python: >=3.7,<4.0
Classifier: License :: OSI Approved :: MIT License
Classifier: Programming Language :: Python :: 3
Classifier: Programming Language :: Python :: 3.10
Classifier: Programming Language :: Python :: 3.7
Classifier: Programming Language :: Python :: 3.8
Classifier: Programming Language :: Python :: 3.9
Requires-Dist: pylint (>=2.15.6,<3.0.0)
Project-URL: Repository, https://github.com/Edge-Center/pylint-blocking-calls
